sdpt3glue
